ai_doc_assistant/__init__.py
ai_doc_assistant/code_analyzer.py
ai_doc_assistant/doc_generator.py
ai_doc_assistant/documentation_generator.py
ai_doc_assistant/model_training.py
ai_doc_assistant/summary_generator.py
ai_doc_assistant/your_code.py
ai_doc_assistant-0.2.dist-info/METADATA
ai_doc_assistant-0.2.dist-info/WHEEL
ai_doc_assistant-0.2.dist-info/top_level.txt
ai_doc_assistant-0.2.dist-info/RECORD
