Metadata-Version: 2.1
Name: ai_doc_assistant
Version: 0.2
Summary: AI-Powered Documentation Assistant for generating code documentation
Author: Thamim Ansari
Author-email: thamimansari358@gmail.com
Classifier: Programming Language :: Python :: 3
Classifier: License :: OSI Approved :: MIT License
Classifier: Operating System :: OS Independent
Requires-Python: >=3.6
Requires-Dist: transformers
Requires-Dist: scikit-learn
Requires-Dist: markdown
Requires-Dist: python-docx
